burp_ui_agent-1.1.1.data/data/share/burpui/etc/buiagent.sample.cfg
burpui_agent/RELEASE
burpui_agent/VERSION
burpui_agent/__init__.py
burpui_agent/__main__.py
burpui_agent/_compat.py
burpui_agent/_json.py
burpui_agent/config.py
burpui_agent/datastructures.py
burpui_agent/decorators.py
burpui_agent/desc.py
burpui_agent/exceptions.py
burpui_agent/security.py
burpui_agent/utils.py
burpui_agent/__pycache__/__init__.cpython-36.pyc
burpui_agent/__pycache__/__init__.cpython-39.pyc
burpui_agent/__pycache__/desc.cpython-36.pyc
burpui_agent/__pycache__/desc.cpython-39.pyc
burpui_agent/engines/__init__.py
burpui_agent/engines/agent.py
burpui_agent/misc/__init__.py
burpui_agent/misc/backend/__init__.py
burpui_agent/misc/backend/burp1.py
burpui_agent/misc/backend/burp2.py
burpui_agent/misc/backend/interface.py
burpui_agent/misc/backend/multi.py
burpui_agent/misc/backend/parallel.py
burpui_agent/misc/backend/.ropeproject/config.py
burpui_agent/misc/backend/.ropeproject/globalnames
burpui_agent/misc/backend/.ropeproject/history
burpui_agent/misc/backend/.ropeproject/objectdb
burpui_agent/misc/backend/utils/__init__.py
burpui_agent/misc/backend/utils/burp2.py
burpui_agent/misc/backend/utils/constant.py
burpui_agent/misc/parser/__init__.py
burpui_agent/misc/parser/burp1.py
burpui_agent/misc/parser/burp2.py
burpui_agent/misc/parser/doc.py
burpui_agent/misc/parser/interface.py
burpui_agent/misc/parser/openssl.py
burpui_agent/misc/parser/utils.py
burpui_agent/misc/parser/.ropeproject/config.py
burpui_agent/misc/parser/.ropeproject/globalnames
burpui_agent/misc/parser/.ropeproject/history
burpui_agent/misc/parser/.ropeproject/objectdb
burpui_agent/tools/__init__.py
burpui_agent/tools/logging.py
burp_ui_agent-1.1.1.dist-info/METADATA
burp_ui_agent-1.1.1.dist-info/WHEEL
burp_ui_agent-1.1.1.dist-info/entry_points.txt
burp_ui_agent-1.1.1.dist-info/top_level.txt
burp_ui_agent-1.1.1.dist-info/RECORD
